setup.cfg
setup.py
kung/__init__.py
kung/kung.py
kung.egg-info/PKG-INFO
kung.egg-info/SOURCES.txt
kung.egg-info/dependency_links.txt
kung.egg-info/entry_points.txt
kung.egg-info/requires.txt
kung.egg-info/top_level.txt
kung.egg-info/zip-safe