Metadata-Version: 1.0
Name: kung
Version: 1.0.2dev
Summary: more with less
Home-page: http://github.com/travisjeffery/kung
Author: Travis Jeffery
Author-email: travisjeffery@gmail.com
License: MIT
Keywords: less more read file
Platform: UNKNOWN
Classifier: Development Status :: 4 - Beta
Classifier: License :: OSI Approved :: MIT License
Classifier: Topic :: Utilities
